configvault/__init__.py
configvault/configvault.py
configvault-0.0.2.dist-info/LICENSE
configvault-0.0.2.dist-info/METADATA
configvault-0.0.2.dist-info/WHEEL
configvault-0.0.2.dist-info/top_level.txt
configvault-0.0.2.dist-info/RECORD
