Metadata-Version: 2.1
Name: configvault
Version: 0.0.2
Summary: Secure, encrypted configuration storage for Python applications
Author-email: "Ioannis D (devcoons)" <support@devcoons.com>
License: MIT License
Project-URL: Homepage, https://github.com/devcoons/configvault
Project-URL: Issues, https://github.com/devcoons/configvault/issues
Project-URL: Documentation, https://github.com/devcoons/configvault/wiki
Project-URL: Source, https://github.com/devcoons/configvault
Keywords: configvault,configuration,encryption,secure storage,config management
Classifier: Development Status :: 4 - Beta
Classifier: Intended Audience :: Developers
Classifier: Natural Language :: English
Classifier: License :: OSI Approved :: MIT License
Classifier: Operating System :: OS Independent
Classifier: Programming Language :: Python :: 3.8
Classifier: Programming Language :: Python :: 3.9
Classifier: Programming Language :: Python :: 3.10
Classifier: Programming Language :: Python :: 3.11
Classifier: Programming Language :: Python :: Implementation :: CPython
Classifier: Topic :: Security :: Cryptography
Requires-Python: >=3.8
License-File: LICENSE
Requires-Dist: cryptography>=3.4.7
Provides-Extra: dev
Requires-Dist: pip-tools; extra == "dev"
Requires-Dist: pytest; extra == "dev"
